[
    {
        "path": "ref",
        "document": {
            "kind": "N",
            "path": [
                "ref"
            ],
            "rhs": "VJPmvFYpx"
        },
        "diff": [
            {
                "count": 9,
                "added": true,
                "value": "VJPmvFYpx"
            }
        ],
        "id": "61af7321-e313-46c2-b823-72ec76178914",
        "createdAt": "2016-03-22T00:55:34.767Z",
        "updatedAt": "2016-03-22T00:55:34.833Z",
        "revisionId": "7325ab21-3299-4da7-892f-fa170c8eb20c"
    },
    {
        "path": "json",
        "document": {
            "kind": "N",
            "path": [
                "json"
            ],
            "rhs": {}
        },
        "diff": [
            {
                "count": 2,
                "added": true,
                "value": "{}"
            }
        ],
        "id": "666e461b-0fe8-40e5-b642-a4a0b616a2c3",
        "createdAt": "2016-03-23T14:38:53.399Z",
        "updatedAt": "2016-03-23T14:38:53.457Z",
        "revisionId": "0d5ea1cb-bbb9-456b-a11c-e180c085b2b9"
    },
    {
        "path": "blocks",
        "document": {
            "kind": "E",
            "path": [
                "blocks",
                "blocks",
                2,
                "key"
            ],
            "lhs": "bseg5",
            "rhs": "a0o1p"
        },
        "diff": [
            {
                "count": 5,
                "removed": true,
                "value": "bseg5"
            },
            {
                "count": 5,
                "added": true,
                "value": "a0o1p"
            }
        ],
        "id": "93341dd1-bd12-44d6-a8e9-a3c0f8002d1f",
        "createdAt": "2016-03-23T11:02:23.432Z",
        "updatedAt": "2016-03-23T11:02:23.496Z",
        "revisionId": "699e6e50-63b2-4835-a132-f29fbe316c40"
    },
    {
        "path": "templateData",
        "document": {
            "kind": "N",
            "path": [
                "templateData"
            ],
            "rhs": {}
        },
        "diff": [
            {
                "count": 2,
                "added": true,
                "value": "{}"
            }
        ],
        "id": "3a185e16-e54f-475c-9bae-7fbb03cdebba",
        "createdAt": "2016-03-22T00:55:34.768Z",
        "updatedAt": "2016-03-22T00:55:34.833Z",
        "revisionId": "7325ab21-3299-4da7-892f-fa170c8eb20c"
    },
    {
        "path": "order",
        "document": {
            "kind": "N",
            "path": [
                "order"
            ],
            "rhs": 0
        },
        "diff": [
            {
                "count": 1,
                "added": true,
                "value": "0"
            }
        ],
        "id": "a13bebe0-3e51-4dc0-8dd8-b8043095e28f",
        "createdAt": "2016-03-22T00:55:34.768Z",
        "updatedAt": "2016-03-22T00:55:34.831Z",
        "revisionId": "7325ab21-3299-4da7-892f-fa170c8eb20c"
    },
    {
        "path": "blocks",
        "document": {
            "kind": "E",
            "path": [
                "blocks"
            ],
            "lhs": [],
            "rhs": {
                "entityMap": {},
                "blocks": [
                    {
                        "key": "bk9qv",
                        "text": "Jadda",
                        "type": "unstyled",
                        "depth": 0,
                        "inlineStyleRanges": [],
                        "entityRanges": []
                    }
                ]
            }
        },
        "diff": [
            {
                "count": 127,
                "added": true,
                "value": "{\"entityMap\":{},\"blocks\":[{\"key\":\"bk9qv\",\"text\":\"Jadda\",\"type\":\"unstyled\",\"depth\":0,\"inlineStyleRanges\":[],\"entityRanges\":[]}]}"
            }
        ],
        "id": "6787c617-b7b0-412a-b2cc-77aa119db1f6",
        "createdAt": "2016-03-22T00:55:44.720Z",
        "updatedAt": "2016-03-22T00:55:44.742Z",
        "revisionId": "8dd1a2a3-6860-409b-80a8-85284a3f2a58"
    },
    {
        "path": "blocks",
        "document": {
            "kind": "N",
            "path": [
                "blocks",
                "entityMap",
                "0"
            ],
            "rhs": {
                "type": "TOKEN",
                "mutability": "MUTABLE",
                "data": {
                    "image": {
                        "id": "b8a49e97-67c7-47a4-9c99-385083796bfe",
                        "ref": "V1HZo9iae",
                        "name": "powr/yrhm50wdy0xel7rt8ixe",
                        "original": "file0001116000079.jpg",
                        "url": "https://res.cloudinary.com/dhsf4vjjc/image/upload/v1458744291/powr/yrhm50wdy0xel7rt8ixe.jpg",
                        "type": "image",
                        "mime": "image/jpg",
                        "height": 1000,
                        "width": 750,
                        "size": 309747,
                        "colorsGoogle": [
                            "blue"
                        ],
                        "colors": [
                            "#2e79d4",
                            "#a6d9f6",
                            "#042e8e",
                            "#6ea8ee",
                            "#6cc4fc"
                        ],
                        "comment": null,
                        "createdAt": "2016-03-23T14:44:52.294Z",
                        "updatedAt": "2016-03-23T14:44:52.294Z",
                        "deletedAt": null,
                        "userId": "f760021d-4fcc-4f3c-bc7f-ab527a11e04e",
                        "tags": []
                    }
                }
            }
        },
        "diff": [
            {
                "count": 617,
                "added": true,
                "value": "{\"type\":\"TOKEN\",\"mutability\":\"MUTABLE\",\"data\":{\"image\":{\"id\":\"b8a49e97-67c7-47a4-9c99-385083796bfe\",\"ref\":\"V1HZo9iae\",\"name\":\"powr/yrhm50wdy0xel7rt8ixe\",\"original\":\"file0001116000079.jpg\",\"url\":\"https://res.cloudinary.com/dhsf4vjjc/image/upload/v1458744291/powr/yrhm50wdy0xel7rt8ixe.jpg\",\"type\":\"image\",\"mime\":\"image/jpg\",\"height\":1000,\"width\":750,\"size\":309747,\"colorsGoogle\":[\"blue\"],\"colors\":[\"#2e79d4\",\"#a6d9f6\",\"#042e8e\",\"#6ea8ee\",\"#6cc4fc\"],\"comment\":null,\"createdAt\":\"2016-03-23T14:44:52.294Z\",\"updatedAt\":\"2016-03-23T14:44:52.294Z\",\"deletedAt\":null,\"userId\":\"f760021d-4fcc-4f3c-bc7f-ab527a11e04e\",\"tags\":[]}}}"
            }
        ],
        "id": "f77acbbd-db16-4b46-bb39-266f383c335a",
        "createdAt": "2016-03-23T14:45:18.813Z",
        "updatedAt": "2016-03-23T14:45:18.861Z",
        "revisionId": "91c93480-88c4-446e-9356-342cf23078d4"
    },
    {
        "path": "order",
        "document": {
            "kind": "E",
            "path": [
                "order"
            ],
            "lhs": 0,
            "rhs": 1
        },
        "diff": [
            {
                "count": 1,
                "removed": true,
                "value": "0"
            },
            {
                "count": 1,
                "added": true,
                "value": "1"
            }
        ],
        "id": "7b8ec0ca-502b-4c7d-9cd5-bde8bbef601c",
        "createdAt": "2016-03-22T00:55:34.872Z",
        "updatedAt": "2016-03-22T00:55:34.895Z",
        "revisionId": "80315e9a-388b-42fd-a7c9-58b503c688f3"
    },
    {
        "path": "blocks",
        "document": {
            "kind": "E",
            "path": [
                "blocks",
                "blocks",
                2,
                "type"
            ],
            "lhs": "Events",
            "rhs": "Image"
        },
        "diff": [
            {
                "count": 2,
                "removed": true,
                "value": "Ev"
            },
            {
                "count": 4,
                "added": true,
                "value": "Imag"
            },
            {
                "count": 1,
                "value": "e"
            },
            {
                "count": 3,
                "removed": true,
                "value": "nts"
            }
        ],
        "id": "1b6a3b87-03f2-4fe7-a19f-816fab25c0bb",
        "createdAt": "2016-03-23T11:02:23.432Z",
        "updatedAt": "2016-03-23T11:02:23.494Z",
        "revisionId": "699e6e50-63b2-4835-a132-f29fbe316c40"
    },
    {
        "path": "blocks",
        "document": {
            "kind": "E",
            "path": [
                "blocks",
                "blocks",
                2,
                "text"
            ],
            "lhs": "",
            "rhs": " "
        },
        "diff": [
            {
                "count": 1,
                "added": true,
                "value": " "
            }
        ],
        "id": "65f80015-a5f5-4f72-a801-9ccaa3e73d87",
        "createdAt": "2016-03-22T14:39:45.341Z",
        "updatedAt": "2016-03-22T14:39:45.385Z",
        "revisionId": "cc379f6d-3638-47da-b1e4-9d2599081c68"
    },
    {
        "path": "blocks",
        "document": {
            "kind": "D",
            "path": [
                "blocks",
                "entityMap",
                "0",
                "data",
                "order"
            ],
            "lhs": [
                [
                    "name",
                    "ASC"
                ]
            ]
        },
        "diff": [
            {
                "count": 16,
                "removed": true,
                "value": "[[\"name\",\"ASC\"]]"
            }
        ],
        "id": "3b11bb42-14ff-4eac-bb12-5f92be9d16f9",
        "createdAt": "2016-03-23T11:02:23.385Z",
        "updatedAt": "2016-03-23T11:02:23.479Z",
        "revisionId": "699e6e50-63b2-4835-a132-f29fbe316c40"
    },
    {
        "path": "placeholder",
        "document": {
            "kind": "N",
            "path": [
                "placeholder"
            ],
            "rhs": false
        },
        "diff": [
            {
                "count": 1,
                "added": true,
                "value": "0"
            }
        ],
        "id": "499d1fb0-4597-47da-9a14-563b7a5d63ad",
        "createdAt": "2016-03-23T14:38:53.398Z",
        "updatedAt": "2016-03-23T14:38:53.455Z",
        "revisionId": "0d5ea1cb-bbb9-456b-a11c-e180c085b2b9"
    },
    {
        "path": "blocks",
        "document": {
            "kind": "N",
            "path": [
                "blocks"
            ],
            "rhs": []
        },
        "diff": [],
        "id": "9fb89bd3-0720-4a1d-a9fb-71ee3112766b",
        "createdAt": "2016-03-23T14:38:53.393Z",
        "updatedAt": "2016-03-23T14:38:53.437Z",
        "revisionId": "0d5ea1cb-bbb9-456b-a11c-e180c085b2b9"
    },
    {
        "path": "blocks",
        "document": {
            "kind": "N",
            "path": [
                "blocks",
                "entityMap",
                "0",
                "data",
                "order"
            ],
            "rhs": [
                [
                    "name",
                    "ASC"
                ]
            ]
        },
        "diff": [
            {
                "count": 16,
                "added": true,
                "value": "[[\"name\",\"ASC\"]]"
            }
        ],
        "id": "48f4b0eb-1a33-4348-b07c-87817669b5a0",
        "createdAt": "2016-03-22T14:45:27.141Z",
        "updatedAt": "2016-03-22T14:45:27.172Z",
        "revisionId": "626dfe54-a80b-4b4b-82ad-d28c709d1592"
    },
    {
        "path": "slug",
        "document": {
            "kind": "N",
            "path": [
                "slug"
            ],
            "rhs": "/jadda"
        },
        "diff": [
            {
                "count": 6,
                "added": true,
                "value": "/jadda"
            }
        ],
        "id": "8a41d246-a960-4098-bdd8-bdac833330c3",
        "createdAt": "2016-03-23T14:38:53.396Z",
        "updatedAt": "2016-03-23T14:38:53.444Z",
        "revisionId": "0d5ea1cb-bbb9-456b-a11c-e180c085b2b9"
    },
    {
        "path": "blocks",
        "document": {
            "kind": "N",
            "path": [
                "blocks",
                "entityMap",
                "0",
                "data",
                "image"
            ],
            "rhs": {
                "id": "06d137fc-097a-4855-9c9e-be696834f576",
                "ref": "EJgYj-9Te",
                "name": "powr/qkmfffutc6tyosf2z4xh",
                "original": "DSC00513.jpg",
                "url": "https://res.cloudinary.com/dhsf4vjjc/image/upload/v1458642014/powr/qkmfffutc6tyosf2z4xh.jpg",
                "type": "image",
                "mime": "image/jpg",
                "height": 3264,
                "width": 4912,
                "size": 2870935,
                "colorsGoogle": [
                    "brown",
                    "gray"
                ],
                "colors": [
                    "#754c42",
                    "#1a1224",
                    "#c1724e",
                    "#c1a986",
                    "#9c8488"
                ],
                "comment": "Hondaa",
                "createdAt": "2016-03-22T10:20:15.459Z",
                "updatedAt": "2016-03-23T11:00:40.008Z",
                "deletedAt": null,
                "userId": "f760021d-4fcc-4f3c-bc7f-ab527a11e04e",
                "tags": [
                    "Hi"
                ]
            }
        },
        "diff": [
            {
                "count": 569,
                "added": true,
                "value": "{\"id\":\"06d137fc-097a-4855-9c9e-be696834f576\",\"ref\":\"EJgYj-9Te\",\"name\":\"powr/qkmfffutc6tyosf2z4xh\",\"original\":\"DSC00513.jpg\",\"url\":\"https://res.cloudinary.com/dhsf4vjjc/image/upload/v1458642014/powr/qkmfffutc6tyosf2z4xh.jpg\",\"type\":\"image\",\"mime\":\"image/jpg\",\"height\":3264,\"width\":4912,\"size\":2870935,\"colorsGoogle\":[\"brown\",\"gray\"],\"colors\":[\"#754c42\",\"#1a1224\",\"#c1724e\",\"#c1a986\",\"#9c8488\"],\"comment\":\"Hondaa\",\"createdAt\":\"2016-03-22T10:20:15.459Z\",\"updatedAt\":\"2016-03-23T11:00:40.008Z\",\"deletedAt\":null,\"userId\":\"f760021d-4fcc-4f3c-bc7f-ab527a11e04e\",\"tags\":[\"Hi\"]}"
            }
        ],
        "id": "ef7e6db5-ccc4-4714-8f70-c687460b3111",
        "createdAt": "2016-03-23T11:02:23.428Z",
        "updatedAt": "2016-03-23T11:02:23.480Z",
        "revisionId": "699e6e50-63b2-4835-a132-f29fbe316c40"
    },
    {
        "path": "blocks",
        "document": {
            "kind": "A",
            "path": [
                "blocks",
                "blocks"
            ],
            "index": 1,
            "item": {
                "kind": "N",
                "rhs": {
                    "key": "onq9",
                    "text": "",
                    "type": "unstyled",
                    "depth": 0,
                    "inlineStyleRanges": [],
                    "entityRanges": []
                }
            }
        },
        "diff": [
            {
                "count": 93,
                "added": true,
                "value": "{\"key\":\"onq9\",\"text\":\"\",\"type\":\"unstyled\",\"depth\":0,\"inlineStyleRanges\":[],\"entityRanges\":[]}"
            }
        ],
        "id": "c15770ce-d965-4092-b2ec-567604c29d67",
        "createdAt": "2016-03-22T14:39:32.032Z",
        "updatedAt": "2016-03-22T14:39:32.061Z",
        "revisionId": "0441a05e-4ac5-42ed-b6f2-fdc03c1c983a"
    },
    {
        "path": "blocks",
        "document": {
            "kind": "N",
            "path": [
                "blocks",
                "entityMap",
                "0"
            ],
            "rhs": {
                "type": "TOKEN",
                "mutability": "MUTABLE",
                "data": {
                    "width": 100
                }
            }
        },
        "diff": [
            {
                "count": 60,
                "added": true,
                "value": "{\"type\":\"TOKEN\",\"mutability\":\"MUTABLE\",\"data\":{\"width\":100}}"
            }
        ],
        "id": "7c7708d5-5a5c-48a2-b22e-9d9564105a6d",
        "createdAt": "2016-03-22T14:39:45.340Z",
        "updatedAt": "2016-03-22T14:39:45.385Z",
        "revisionId": "cc379f6d-3638-47da-b1e4-9d2599081c68"
    },
    {
        "path": "blocks",
        "document": {
            "kind": "A",
            "path": [
                "blocks",
                "blocks"
            ],
            "index": 4,
            "item": {
                "kind": "N",
                "rhs": {
                    "key": "8gti6",
                    "text": "",
                    "type": "unstyled",
                    "depth": 0,
                    "inlineStyleRanges": [],
                    "entityRanges": []
                }
            }
        },
        "diff": [
            {
                "count": 94,
                "added": true,
                "value": "{\"key\":\"8gti6\",\"text\":\"\",\"type\":\"unstyled\",\"depth\":0,\"inlineStyleRanges\":[],\"entityRanges\":[]}"
            }
        ],
        "id": "dceb26c5-78a4-441c-9333-5f8195488123",
        "createdAt": "2016-03-22T14:39:32.042Z",
        "updatedAt": "2016-03-22T14:39:32.066Z",
        "revisionId": "0441a05e-4ac5-42ed-b6f2-fdc03c1c983a"
    },
    {
        "path": "order",
        "document": {
            "kind": "E",
            "path": [
                "order"
            ],
            "lhs": 0,
            "rhs": 1
        },
        "diff": [
            {
                "count": 1,
                "removed": true,
                "value": "0"
            },
            {
                "count": 1,
                "added": true,
                "value": "1"
            }
        ],
        "id": "7d8c0bee-14e8-4596-ada2-eb9c1c0f94f4",
        "createdAt": "2016-03-23T14:38:53.501Z",
        "updatedAt": "2016-03-23T14:38:53.526Z",
        "revisionId": "0aea22f1-1728-4a7f-bbd4-85a9a70e0d40"
    },
    {
        "path": "json",
        "document": {
            "kind": "N",
            "path": [
                "json"
            ],
            "rhs": {}
        },
        "diff": [
            {
                "count": 2,
                "added": true,
                "value": "{}"
            }
        ],
        "id": "3f3242d9-5722-4579-be5e-79f91a087c28",
        "createdAt": "2016-03-22T00:55:34.768Z",
        "updatedAt": "2016-03-22T00:55:34.832Z",
        "revisionId": "7325ab21-3299-4da7-892f-fa170c8eb20c"
    },
    {
        "path": "blocks",
        "document": {
            "kind": "N",
            "path": [
                "blocks"
            ],
            "rhs": []
        },
        "diff": [],
        "id": "84a9eefd-242f-4d38-a98e-1b45fcc6c914",
        "createdAt": "2016-03-22T00:55:34.764Z",
        "updatedAt": "2016-03-22T00:55:34.819Z",
        "revisionId": "7325ab21-3299-4da7-892f-fa170c8eb20c"
    },
    {
        "path": "blocks",
        "document": {
            "kind": "A",
            "path": [
                "blocks",
                "blocks"
            ],
            "index": 5,
            "item": {
                "kind": "N",
                "rhs": {
                    "key": "5c99s",
                    "text": "",
                    "type": "unstyled",
                    "depth": 0,
                    "inlineStyleRanges": [],
                    "entityRanges": []
                }
            }
        },
        "diff": [
            {
                "count": 94,
                "added": true,
                "value": "{\"key\":\"5c99s\",\"text\":\"\",\"type\":\"unstyled\",\"depth\":0,\"inlineStyleRanges\":[],\"entityRanges\":[]}"
            }
        ],
        "id": "03b1697a-747e-4bb5-888e-f06fd81c21fc",
        "createdAt": "2016-03-23T11:02:23.438Z",
        "updatedAt": "2016-03-23T11:02:23.509Z",
        "revisionId": "699e6e50-63b2-4835-a132-f29fbe316c40"
    },
    {
        "path": "blocks",
        "document": {
            "kind": "E",
            "path": [
                "blocks",
                "blocks",
                3,
                "key"
            ],
            "lhs": "5c99s",
            "rhs": "onq9"
        },
        "diff": [
            {
                "count": 2,
                "removed": true,
                "value": "5c"
            },
            {
                "count": 3,
                "added": true,
                "value": "onq"
            },
            {
                "count": 1,
                "value": "9"
            },
            {
                "count": 2,
                "removed": true,
                "value": "9s"
            }
        ],
        "id": "8c329228-64d3-4083-87b4-5307778e32ad",
        "createdAt": "2016-03-23T11:02:23.433Z",
        "updatedAt": "2016-03-23T11:02:23.495Z",
        "revisionId": "699e6e50-63b2-4835-a132-f29fbe316c40"
    },
    {
        "path": "ref",
        "document": {
            "kind": "N",
            "path": [
                "ref"
            ],
            "rhs": "Vk0cY9opx"
        },
        "diff": [
            {
                "count": 9,
                "added": true,
                "value": "Vk0cY9opx"
            }
        ],
        "id": "0b8107b3-3b58-42c2-bffe-cab5533ad6f9",
        "createdAt": "2016-03-23T14:38:53.398Z",
        "updatedAt": "2016-03-23T14:38:53.444Z",
        "revisionId": "0d5ea1cb-bbb9-456b-a11c-e180c085b2b9"
    },
    {
        "path": "order",
        "document": {
            "kind": "E",
            "path": [
                "order"
            ],
            "lhs": 1,
            "rhs": 2
        },
        "diff": [
            {
                "count": 1,
                "removed": true,
                "value": "1"
            },
            {
                "count": 1,
                "added": true,
                "value": "2"
            }
        ],
        "id": "27a2b82f-7b22-40ab-aa80-cac5550ed2fd",
        "createdAt": "2016-03-23T14:38:53.518Z",
        "updatedAt": "2016-03-23T14:38:53.531Z",
        "revisionId": "f153221d-4c52-40e8-83b3-0fb5322d262f"
    },
    {
        "path": "blocks",
        "document": {
            "kind": "A",
            "path": [
                "blocks",
                "blocks"
            ],
            "index": 3,
            "item": {
                "kind": "N",
                "rhs": {
                    "key": "5c99s",
                    "text": "",
                    "type": "unstyled",
                    "depth": 0,
                    "inlineStyleRanges": [],
                    "entityRanges": []
                }
            }
        },
        "diff": [
            {
                "count": 94,
                "added": true,
                "value": "{\"key\":\"5c99s\",\"text\":\"\",\"type\":\"unstyled\",\"depth\":0,\"inlineStyleRanges\":[],\"entityRanges\":[]}"
            }
        ],
        "id": "6773e941-34f6-4325-a3a8-a662a5908de3",
        "createdAt": "2016-03-22T14:39:32.041Z",
        "updatedAt": "2016-03-22T14:39:32.065Z",
        "revisionId": "0441a05e-4ac5-42ed-b6f2-fdc03c1c983a"
    },
    {
        "path": "templateData",
        "document": {
            "kind": "N",
            "path": [
                "templateData"
            ],
            "rhs": {}
        },
        "diff": [
            {
                "count": 2,
                "added": true,
                "value": "{}"
            }
        ],
        "id": "dce53d6f-b69f-4521-a888-ea2fefdcf63f",
        "createdAt": "2016-03-23T14:38:53.399Z",
        "updatedAt": "2016-03-23T14:38:53.456Z",
        "revisionId": "0d5ea1cb-bbb9-456b-a11c-e180c085b2b9"
    },
    {
        "path": "name",
        "document": {
            "kind": "N",
            "path": [
                "name"
            ],
            "rhs": "Jadda"
        },
        "diff": [
            {
                "count": 5,
                "added": true,
                "value": "Jadda"
            }
        ],
        "id": "b0fdf879-d448-49a3-b2ab-5a06feb03c67",
        "createdAt": "2016-03-23T14:38:53.396Z",
        "updatedAt": "2016-03-23T14:38:53.443Z",
        "revisionId": "0d5ea1cb-bbb9-456b-a11c-e180c085b2b9"
    },
    {
        "path": "blocks",
        "document": {
            "kind": "A",
            "path": [
                "blocks",
                "blocks"
            ],
            "index": 3,
            "item": {
                "kind": "D",
                "lhs": {
                    "key": "onq9",
                    "text": "",
                    "type": "unstyled",
                    "depth": 0,
                    "inlineStyleRanges": [],
                    "entityRanges": []
                }
            }
        },
        "diff": [
            {
                "count": 93,
                "removed": true,
                "value": "{\"key\":\"onq9\",\"text\":\"\",\"type\":\"unstyled\",\"depth\":0,\"inlineStyleRanges\":[],\"entityRanges\":[]}"
            }
        ],
        "id": "65d5f6dc-1ae0-4600-977f-1d7fd90a4245",
        "createdAt": "2016-05-04T08:04:46.868Z",
        "updatedAt": "2016-05-04T08:04:46.929Z",
        "revisionId": "d2b51ea8-bade-4771-a274-2f49de5fa84e"
    },
    {
        "path": "order",
        "document": {
            "kind": "N",
            "path": [
                "order"
            ],
            "rhs": 0
        },
        "diff": [
            {
                "count": 1,
                "added": true,
                "value": "0"
            }
        ],
        "id": "273289b6-d416-4beb-ad44-e984c8395104",
        "createdAt": "2016-03-23T14:38:53.399Z",
        "updatedAt": "2016-03-23T14:38:53.457Z",
        "revisionId": "0d5ea1cb-bbb9-456b-a11c-e180c085b2b9"
    },
    {
        "path": "menu",
        "document": {
            "kind": "N",
            "path": [
                "menu"
            ],
            "rhs": null
        },
        "diff": [],
        "id": "a1d57837-3065-4a8e-ad31-9c44eaa70e82",
        "createdAt": "2016-03-23T14:38:53.397Z",
        "updatedAt": "2016-03-23T14:38:53.445Z",
        "revisionId": "0d5ea1cb-bbb9-456b-a11c-e180c085b2b9"
    },
    {
        "path": "blocks",
        "document": {
            "kind": "E",
            "path": [
                "blocks",
                "blocks",
                0,
                "text"
            ],
            "lhs": "Jadda",
            "rhs": "qwdqwd"
        },
        "diff": [
            {
                "count": 2,
                "removed": true,
                "value": "Ja"
            },
            {
                "count": 2,
                "added": true,
                "value": "qw"
            },
            {
                "count": 1,
                "value": "d"
            },
            {
                "count": 2,
                "added": true,
                "value": "qw"
            },
            {
                "count": 1,
                "value": "d"
            },
            {
                "count": 1,
                "removed": true,
                "value": "a"
            }
        ],
        "id": "9a81c974-4ca3-4728-90f9-7eb682f4efad",
        "createdAt": "2016-05-04T08:04:46.863Z",
        "updatedAt": "2016-05-04T08:04:46.912Z",
        "revisionId": "d2b51ea8-bade-4771-a274-2f49de5fa84e"
    },
    {
        "path": "slug",
        "document": {
            "kind": "N",
            "path": [
                "slug"
            ],
            "rhs": "/hallo"
        },
        "diff": [
            {
                "count": 6,
                "added": true,
                "value": "/hallo"
            }
        ],
        "id": "20bc3f20-af47-435f-afe9-747046611850",
        "createdAt": "2016-03-22T00:55:34.767Z",
        "updatedAt": "2016-03-22T00:55:34.820Z",
        "revisionId": "7325ab21-3299-4da7-892f-fa170c8eb20c"
    },
    {
        "path": "blocks",
        "document": {
            "kind": "E",
            "path": [
                "blocks"
            ],
            "lhs": [],
            "rhs": {
                "entityMap": {},
                "blocks": [
                    {
                        "key": "eqno3",
                        "text": "Test",
                        "type": "unstyled",
                        "depth": 0,
                        "inlineStyleRanges": [],
                        "entityRanges": []
                    }
                ]
            }
        },
        "diff": [
            {
                "count": 126,
                "added": true,
                "value": "{\"entityMap\":{},\"blocks\":[{\"key\":\"eqno3\",\"text\":\"Test\",\"type\":\"unstyled\",\"depth\":0,\"inlineStyleRanges\":[],\"entityRanges\":[]}]}"
            }
        ],
        "id": "c629dfbb-9a0f-43dc-b22d-45df678aa2e6",
        "createdAt": "2016-03-23T14:38:58.682Z",
        "updatedAt": "2016-03-23T14:38:58.712Z",
        "revisionId": "7d7314ae-874c-4958-be52-c311ca72a9f3"
    },
    {
        "path": "blocks",
        "document": {
            "kind": "D",
            "path": [
                "blocks",
                "entityMap",
                "0",
                "data",
                "width"
            ],
            "lhs": 100
        },
        "diff": [
            {
                "count": 3,
                "removed": true,
                "value": "100"
            }
        ],
        "id": "a062f209-6222-4474-8a61-f123024f0460",
        "createdAt": "2016-03-23T11:02:23.383Z",
        "updatedAt": "2016-03-23T11:02:23.473Z",
        "revisionId": "699e6e50-63b2-4835-a132-f29fbe316c40"
    },
    {
        "path": "blocks",
        "document": {
            "kind": "A",
            "path": [
                "blocks",
                "blocks"
            ],
            "index": 2,
            "item": {
                "kind": "N",
                "rhs": {
                    "key": "4hvv0",
                    "text": " ",
                    "type": "Image",
                    "depth": 0,
                    "inlineStyleRanges": [],
                    "entityRanges": [
                        {
                            "offset": 0,
                            "length": 1,
                            "key": 0
                        }
                    ]
                }
            }
        },
        "diff": [
            {
                "count": 123,
                "added": true,
                "value": "{\"key\":\"4hvv0\",\"text\":\" \",\"type\":\"Image\",\"depth\":0,\"inlineStyleRanges\":[],\"entityRanges\":[{\"offset\":0,\"length\":1,\"key\":0}]}"
            }
        ],
        "id": "572f5bd1-83fa-495b-a1eb-f3b984d62185",
        "createdAt": "2016-03-23T14:45:18.818Z",
        "updatedAt": "2016-03-23T14:45:18.861Z",
        "revisionId": "91c93480-88c4-446e-9356-342cf23078d4"
    },
    {
        "path": "blocks",
        "document": {
            "kind": "A",
            "path": [
                "blocks",
                "blocks",
                4,
                "entityRanges"
            ],
            "index": 0,
            "item": {
                "kind": "N",
                "rhs": {
                    "offset": 0,
                    "length": 1,
                    "key": 1
                }
            }
        },
        "diff": [
            {
                "count": 31,
                "added": true,
                "value": "{\"offset\":0,\"length\":1,\"key\":1}"
            }
        ],
        "id": "e24071c7-5bd6-4849-8ef7-bfa28d5fbb0b",
        "createdAt": "2016-03-23T11:02:23.434Z",
        "updatedAt": "2016-03-23T11:02:23.509Z",
        "revisionId": "699e6e50-63b2-4835-a132-f29fbe316c40"
    },
    {
        "path": "blocks",
        "document": {
            "kind": "E",
            "path": [
                "blocks",
                "blocks",
                2,
                "type"
            ],
            "lhs": "unstyled",
            "rhs": "Events"
        },
        "diff": [
            {
                "count": 1,
                "removed": true,
                "value": "u"
            },
            {
                "count": 3,
                "added": true,
                "value": "Eve"
            },
            {
                "count": 1,
                "value": "n"
            },
            {
                "count": 1,
                "added": true,
                "value": "t"
            },
            {
                "count": 1,
                "value": "s"
            },
            {
                "count": 5,
                "removed": true,
                "value": "tyled"
            }
        ],
        "id": "ef73c492-d73f-486f-b5ed-8d6528e63f63",
        "createdAt": "2016-03-22T14:39:45.342Z",
        "updatedAt": "2016-03-22T14:39:45.384Z",
        "revisionId": "cc379f6d-3638-47da-b1e4-9d2599081c68"
    },
    {
        "path": "blocks",
        "document": {
            "kind": "E",
            "path": [
                "blocks",
                "blocks",
                1,
                "key"
            ],
            "lhs": "onq9",
            "rhs": "6mlqg"
        },
        "diff": [
            {
                "count": 2,
                "removed": true,
                "value": "on"
            },
            {
                "count": 3,
                "added": true,
                "value": "6ml"
            },
            {
                "count": 1,
                "value": "q"
            },
            {
                "count": 1,
                "removed": true,
                "value": "9"
            },
            {
                "count": 1,
                "added": true,
                "value": "g"
            }
        ],
        "id": "01bb36e4-3c38-4350-a3cf-5e55e87ebb8b",
        "createdAt": "2016-03-23T11:02:23.432Z",
        "updatedAt": "2016-03-23T11:02:23.480Z",
        "revisionId": "699e6e50-63b2-4835-a132-f29fbe316c40"
    },
    {
        "path": "blocks",
        "document": {
            "kind": "A",
            "path": [
                "blocks",
                "blocks"
            ],
            "index": 2,
            "item": {
                "kind": "D",
                "lhs": {
                    "key": "a0o1p",
                    "text": " ",
                    "type": "Image",
                    "depth": 0,
                    "inlineStyleRanges": [],
                    "entityRanges": [
                        {
                            "offset": 0,
                            "length": 1,
                            "key": 0
                        }
                    ]
                }
            }
        },
        "diff": [
            {
                "count": 123,
                "removed": true,
                "value": "{\"key\":\"a0o1p\",\"text\":\" \",\"type\":\"Image\",\"depth\":0,\"inlineStyleRanges\":[],\"entityRanges\":[{\"offset\":0,\"length\":1,\"key\":0}]}"
            }
        ],
        "id": "22dfa85e-42ce-4812-98fe-8bb8ba4a5d58",
        "createdAt": "2016-05-04T08:04:46.867Z",
        "updatedAt": "2016-05-04T08:04:46.928Z",
        "revisionId": "d2b51ea8-bade-4771-a274-2f49de5fa84e"
    },
    {
        "path": "blocks",
        "document": {
            "kind": "A",
            "path": [
                "blocks",
                "blocks"
            ],
            "index": 2,
            "item": {
                "kind": "N",
                "rhs": {
                    "key": "bseg5",
                    "text": "",
                    "type": "unstyled",
                    "depth": 0,
                    "inlineStyleRanges": [],
                    "entityRanges": []
                }
            }
        },
        "diff": [
            {
                "count": 94,
                "added": true,
                "value": "{\"key\":\"bseg5\",\"text\":\"\",\"type\":\"unstyled\",\"depth\":0,\"inlineStyleRanges\":[],\"entityRanges\":[]}"
            }
        ],
        "id": "2b0317c3-9c1b-4532-9e00-b29d183483c6",
        "createdAt": "2016-03-22T14:39:32.035Z",
        "updatedAt": "2016-03-22T14:39:32.060Z",
        "revisionId": "0441a05e-4ac5-42ed-b6f2-fdc03c1c983a"
    },
    {
        "path": "name",
        "document": {
            "kind": "N",
            "path": [
                "name"
            ],
            "rhs": "Hallo"
        },
        "diff": [
            {
                "count": 5,
                "added": true,
                "value": "Hallo"
            }
        ],
        "id": "0a86e277-435f-4735-8092-8edcdcce9462",
        "createdAt": "2016-03-22T00:55:34.767Z",
        "updatedAt": "2016-03-22T00:55:34.820Z",
        "revisionId": "7325ab21-3299-4da7-892f-fa170c8eb20c"
    },
    {
        "path": "blocks",
        "document": {
            "kind": "A",
            "path": [
                "blocks",
                "blocks"
            ],
            "index": 6,
            "item": {
                "kind": "N",
                "rhs": {
                    "key": "8gti6",
                    "text": "",
                    "type": "unstyled",
                    "depth": 0,
                    "inlineStyleRanges": [],
                    "entityRanges": []
                }
            }
        },
        "diff": [
            {
                "count": 94,
                "added": true,
                "value": "{\"key\":\"8gti6\",\"text\":\"\",\"type\":\"unstyled\",\"depth\":0,\"inlineStyleRanges\":[],\"entityRanges\":[]}"
            }
        ],
        "id": "196a1096-1521-4947-800a-116cb8ae03d2",
        "createdAt": "2016-03-23T11:02:23.439Z",
        "updatedAt": "2016-03-23T11:02:23.509Z",
        "revisionId": "699e6e50-63b2-4835-a132-f29fbe316c40"
    },
    {
        "path": "blocks",
        "document": {
            "kind": "D",
            "path": [
                "blocks",
                "entityMap",
                "1"
            ],
            "lhs": {
                "type": "TOKEN",
                "mutability": "MUTABLE",
                "data": {
                    "width": 100,
                    "order": [
                        [
                            "name",
                            "ASC"
                        ]
                    ]
                }
            }
        },
        "diff": [
            {
                "count": 85,
                "removed": true,
                "value": "{\"type\":\"TOKEN\",\"mutability\":\"MUTABLE\",\"data\":{\"width\":100,\"order\":[[\"name\",\"ASC\"]]}}"
            }
        ],
        "id": "28472424-0387-4997-bc58-f0d71788810c",
        "createdAt": "2016-05-04T08:04:46.862Z",
        "updatedAt": "2016-05-04T08:04:46.915Z",
        "revisionId": "d2b51ea8-bade-4771-a274-2f49de5fa84e"
    },
    {
        "path": "blocks",
        "document": {
            "kind": "E",
            "path": [
                "blocks",
                "blocks",
                4,
                "key"
            ],
            "lhs": "8gti6",
            "rhs": "bseg5"
        },
        "diff": [
            {
                "count": 1,
                "removed": true,
                "value": "8"
            },
            {
                "count": 3,
                "added": true,
                "value": "bse"
            },
            {
                "count": 1,
                "value": "g"
            },
            {
                "count": 3,
                "removed": true,
                "value": "ti6"
            },
            {
                "count": 1,
                "added": true,
                "value": "5"
            }
        ],
        "id": "257a440f-41c4-4f2b-b2d1-71cb506a7fe6",
        "createdAt": "2016-03-23T11:02:23.433Z",
        "updatedAt": "2016-03-23T11:02:23.495Z",
        "revisionId": "699e6e50-63b2-4835-a132-f29fbe316c40"
    },
    {
        "path": "blocks",
        "document": {
            "kind": "A",
            "path": [
                "blocks",
                "blocks"
            ],
            "index": 4,
            "item": {
                "kind": "D",
                "lhs": {
                    "key": "bseg5",
                    "text": " ",
                    "type": "Events",
                    "depth": 0,
                    "inlineStyleRanges": [],
                    "entityRanges": [
                        {
                            "offset": 0,
                            "length": 1,
                            "key": 1
                        }
                    ]
                }
            }
        },
        "diff": [
            {
                "count": 124,
                "removed": true,
                "value": "{\"key\":\"bseg5\",\"text\":\" \",\"type\":\"Events\",\"depth\":0,\"inlineStyleRanges\":[],\"entityRanges\":[{\"offset\":0,\"length\":1,\"key\":1}]}"
            }
        ],
        "id": "9c3120ce-9040-4238-9e73-ac077d5b12bd",
        "createdAt": "2016-05-04T08:04:46.871Z",
        "updatedAt": "2016-05-04T08:04:46.930Z",
        "revisionId": "d2b51ea8-bade-4771-a274-2f49de5fa84e"
    },
    {
        "path": "blocks",
        "document": {
            "kind": "E",
            "path": [
                "blocks",
                "blocks",
                4,
                "text"
            ],
            "lhs": "",
            "rhs": " "
        },
        "diff": [
            {
                "count": 1,
                "added": true,
                "value": " "
            }
        ],
        "id": "a4404c34-1542-4a3c-97a9-06e4dc0ab4ab",
        "createdAt": "2016-03-23T11:02:23.433Z",
        "updatedAt": "2016-03-23T11:02:23.495Z",
        "revisionId": "699e6e50-63b2-4835-a132-f29fbe316c40"
    },
    {
        "path": "blocks",
        "document": {
            "kind": "N",
            "path": [
                "blocks",
                "entityMap",
                "1"
            ],
            "rhs": {
                "type": "TOKEN",
                "mutability": "MUTABLE",
                "data": {
                    "width": 100,
                    "order": [
                        [
                            "name",
                            "ASC"
                        ]
                    ]
                }
            }
        },
        "diff": [
            {
                "count": 85,
                "added": true,
                "value": "{\"type\":\"TOKEN\",\"mutability\":\"MUTABLE\",\"data\":{\"width\":100,\"order\":[[\"name\",\"ASC\"]]}}"
            }
        ],
        "id": "a6c7c386-2b72-4efe-b750-81e50cf6d5f8",
        "createdAt": "2016-03-23T11:02:23.431Z",
        "updatedAt": "2016-03-23T11:02:23.481Z",
        "revisionId": "699e6e50-63b2-4835-a132-f29fbe316c40"
    },
    {
        "path": "blocks",
        "document": {
            "kind": "A",
            "path": [
                "blocks",
                "blocks"
            ],
            "index": 6,
            "item": {
                "kind": "D",
                "lhs": {
                    "key": "8gti6",
                    "text": "",
                    "type": "unstyled",
                    "depth": 0,
                    "inlineStyleRanges": [],
                    "entityRanges": []
                }
            }
        },
        "diff": [
            {
                "count": 94,
                "removed": true,
                "value": "{\"key\":\"8gti6\",\"text\":\"\",\"type\":\"unstyled\",\"depth\":0,\"inlineStyleRanges\":[],\"entityRanges\":[]}"
            }
        ],
        "id": "3b51d3f0-067a-4c62-934b-c1b059a96f77",
        "createdAt": "2016-05-04T08:04:46.873Z",
        "updatedAt": "2016-05-04T08:04:46.947Z",
        "revisionId": "d2b51ea8-bade-4771-a274-2f49de5fa84e"
    },
    {
        "path": "blocks",
        "document": {
            "kind": "D",
            "path": [
                "blocks",
                "entityMap",
                "0"
            ],
            "lhs": {
                "type": "TOKEN",
                "mutability": "MUTABLE",
                "data": {
                    "image": {
                        "id": "06d137fc-097a-4855-9c9e-be696834f576",
                        "ref": "EJgYj-9Te",
                        "name": "powr/qkmfffutc6tyosf2z4xh",
                        "original": "DSC00513.jpg",
                        "url": "https://res.cloudinary.com/dhsf4vjjc/image/upload/v1458642014/powr/qkmfffutc6tyosf2z4xh.jpg",
                        "type": "image",
                        "mime": "image/jpg",
                        "height": 3264,
                        "width": 4912,
                        "size": 2870935,
                        "colorsGoogle": [
                            "brown",
                            "gray"
                        ],
                        "colors": [
                            "#754c42",
                            "#1a1224",
                            "#c1724e",
                            "#c1a986",
                            "#9c8488"
                        ],
                        "comment": "Hondaa",
                        "createdAt": "2016-03-22T10:20:15.459Z",
                        "updatedAt": "2016-03-23T11:00:40.008Z",
                        "deletedAt": null,
                        "userId": "f760021d-4fcc-4f3c-bc7f-ab527a11e04e",
                        "tags": [
                            "Hi"
                        ]
                    }
                }
            }
        },
        "diff": [
            {
                "count": 626,
                "removed": true,
                "value": "{\"type\":\"TOKEN\",\"mutability\":\"MUTABLE\",\"data\":{\"image\":{\"id\":\"06d137fc-097a-4855-9c9e-be696834f576\",\"ref\":\"EJgYj-9Te\",\"name\":\"powr/qkmfffutc6tyosf2z4xh\",\"original\":\"DSC00513.jpg\",\"url\":\"https://res.cloudinary.com/dhsf4vjjc/image/upload/v1458642014/powr/qkmfffutc6tyosf2z4xh.jpg\",\"type\":\"image\",\"mime\":\"image/jpg\",\"height\":3264,\"width\":4912,\"size\":2870935,\"colorsGoogle\":[\"brown\",\"gray\"],\"colors\":[\"#754c42\",\"#1a1224\",\"#c1724e\",\"#c1a986\",\"#9c8488\"],\"comment\":\"Hondaa\",\"createdAt\":\"2016-03-22T10:20:15.459Z\",\"updatedAt\":\"2016-03-23T11:00:40.008Z\",\"deletedAt\":null,\"userId\":\"f760021d-4fcc-4f3c-bc7f-ab527a11e04e\",\"tags\":[\"Hi\"]}}}"
            }
        ],
        "id": "8c9cc1fa-55ae-4330-9dac-e6b5290c6cd0",
        "createdAt": "2016-05-04T08:04:46.860Z",
        "updatedAt": "2016-05-04T08:04:46.897Z",
        "revisionId": "d2b51ea8-bade-4771-a274-2f49de5fa84e"
    },
    {
        "path": "blocks",
        "document": {
            "kind": "A",
            "path": [
                "blocks",
                "blocks"
            ],
            "index": 1,
            "item": {
                "kind": "D",
                "lhs": {
                    "key": "6mlqg",
                    "text": "",
                    "type": "unstyled",
                    "depth": 0,
                    "inlineStyleRanges": [],
                    "entityRanges": []
                }
            }
        },
        "diff": [
            {
                "count": 94,
                "removed": true,
                "value": "{\"key\":\"6mlqg\",\"text\":\"\",\"type\":\"unstyled\",\"depth\":0,\"inlineStyleRanges\":[],\"entityRanges\":[]}"
            }
        ],
        "id": "18b3f2db-8a51-4ee5-8ada-e5088e8a05f5",
        "createdAt": "2016-05-04T08:04:46.865Z",
        "updatedAt": "2016-05-04T08:04:46.910Z",
        "revisionId": "d2b51ea8-bade-4771-a274-2f49de5fa84e"
    },
    {
        "path": "placeholder",
        "document": {
            "kind": "N",
            "path": [
                "placeholder"
            ],
            "rhs": false
        },
        "diff": [
            {
                "count": 1,
                "added": true,
                "value": "0"
            }
        ],
        "id": "4de7de4e-7fae-4879-9423-cf59b0f5df20",
        "createdAt": "2016-03-22T00:55:34.768Z",
        "updatedAt": "2016-03-22T00:55:34.836Z",
        "revisionId": "7325ab21-3299-4da7-892f-fa170c8eb20c"
    },
    {
        "path": "blocks",
        "document": {
            "kind": "A",
            "path": [
                "blocks",
                "blocks"
            ],
            "index": 1,
            "item": {
                "kind": "N",
                "rhs": {
                    "key": "fck27",
                    "text": "",
                    "type": "unstyled",
                    "depth": 0,
                    "inlineStyleRanges": [],
                    "entityRanges": []
                }
            }
        },
        "diff": [
            {
                "count": 94,
                "added": true,
                "value": "{\"key\":\"fck27\",\"text\":\"\",\"type\":\"unstyled\",\"depth\":0,\"inlineStyleRanges\":[],\"entityRanges\":[]}"
            }
        ],
        "id": "a827dd60-87a2-4248-8c45-bc1100a29c51",
        "createdAt": "2016-03-23T14:45:18.814Z",
        "updatedAt": "2016-03-23T14:45:18.860Z",
        "revisionId": "91c93480-88c4-446e-9356-342cf23078d4"
    },
    {
        "path": "blocks",
        "document": {
            "kind": "A",
            "path": [
                "blocks",
                "blocks"
            ],
            "index": 5,
            "item": {
                "kind": "D",
                "lhs": {
                    "key": "5c99s",
                    "text": "",
                    "type": "unstyled",
                    "depth": 0,
                    "inlineStyleRanges": [],
                    "entityRanges": []
                }
            }
        },
        "diff": [
            {
                "count": 94,
                "removed": true,
                "value": "{\"key\":\"5c99s\",\"text\":\"\",\"type\":\"unstyled\",\"depth\":0,\"inlineStyleRanges\":[],\"entityRanges\":[]}"
            }
        ],
        "id": "770efa8f-3675-4c96-b90d-b64f22859199",
        "createdAt": "2016-05-04T08:04:46.872Z",
        "updatedAt": "2016-05-04T08:04:46.933Z",
        "revisionId": "d2b51ea8-bade-4771-a274-2f49de5fa84e"
    },
    {
        "path": "blocks",
        "document": {
            "kind": "E",
            "path": [
                "blocks",
                "blocks",
                0,
                "key"
            ],
            "lhs": "bk9qv",
            "rhs": "6s5lg"
        },
        "diff": [
            {
                "count": 5,
                "removed": true,
                "value": "bk9qv"
            },
            {
                "count": 5,
                "added": true,
                "value": "6s5lg"
            }
        ],
        "id": "a610a984-bae3-401c-a250-ee251b9e9424",
        "createdAt": "2016-05-04T08:04:46.862Z",
        "updatedAt": "2016-05-04T08:04:46.913Z",
        "revisionId": "d2b51ea8-bade-4771-a274-2f49de5fa84e"
    },
    {
        "path": "blocks",
        "document": {
            "kind": "A",
            "path": [
                "blocks",
                "blocks",
                2,
                "entityRanges"
            ],
            "index": 0,
            "item": {
                "kind": "N",
                "rhs": {
                    "offset": 0,
                    "length": 1,
                    "key": 0
                }
            }
        },
        "diff": [
            {
                "count": 31,
                "added": true,
                "value": "{\"offset\":0,\"length\":1,\"key\":0}"
            }
        ],
        "id": "545ec9ab-e2a4-40da-9815-822191dad1dd",
        "createdAt": "2016-03-22T14:39:45.343Z",
        "updatedAt": "2016-03-22T14:39:45.391Z",
        "revisionId": "cc379f6d-3638-47da-b1e4-9d2599081c68"
    },
    {
        "path": "blocks",
        "document": {
            "kind": "E",
            "path": [
                "blocks",
                "blocks",
                4,
                "type"
            ],
            "lhs": "unstyled",
            "rhs": "Events"
        },
        "diff": [
            {
                "count": 1,
                "removed": true,
                "value": "u"
            },
            {
                "count": 3,
                "added": true,
                "value": "Eve"
            },
            {
                "count": 1,
                "value": "n"
            },
            {
                "count": 1,
                "added": true,
                "value": "t"
            },
            {
                "count": 1,
                "value": "s"
            },
            {
                "count": 5,
                "removed": true,
                "value": "tyled"
            }
        ],
        "id": "b9d36245-3319-482c-8a58-4df9330d1b56",
        "createdAt": "2016-03-23T11:02:23.434Z",
        "updatedAt": "2016-03-23T11:02:23.508Z",
        "revisionId": "699e6e50-63b2-4835-a132-f29fbe316c40"
    }
]